README.rst
setup.py
iex/__init__.py
iex/base.py
iex/reference.py
iex/stats.py
iex/stock.py
iex.egg-info/PKG-INFO
iex.egg-info/SOURCES.txt
iex.egg-info/dependency_links.txt
iex.egg-info/requires.txt
iex.egg-info/top_level.txt
iex/market/__init__.py
iex/market/deep.py
iex/market/hist.py
iex/market/tops.py