Metadata-Version: 1.1
Name: iex
Version: 0.0.1
Summary: A module to retrieve stock data from IEX
Home-page: UNKNOWN
Author: Iulian Udrea
Author-email: iulian.udrea14@alumni.imperial.ac.uk
License: Apache License 2.0
Keywords: iex stock market exchange finance trades
Platform: UNKNOWN
Classifier: Development Status :: 1 - Planning
Classifier: Intended Audience :: Developers
Classifier: Intended Audience :: Financial and Insurance Industry
Classifier: Topic :: Office/Business :: Financial :: Investment
Classifier: Topic :: Software Development :: Libraries :: Python Modules
Classifier: Operating System :: OS Independent
Classifier: License :: OSI Approved :: Apache Software License
Classifier: Programming Language :: Python :: 3.6
